[
    {
        "id": 1,
        "rarity": 3,
        "level": 0,
        "total_exp": 0
    },
    {
        "id": 2,
        "rarity": 3,
        "level": 1,
        "total_exp": 12
    },
    {
        "id": 3,
        "rarity": 3,
        "level": 2,
        "total_exp": 32
    },
    {
        "id": 4,
        "rarity": 3,
        "level": 3,
        "total_exp": 66
    },
    {
        "id": 5,
        "rarity": 3,
        "level": 4,
        "total_exp": 124
    },
    {
        "id": 6,
        "rarity": 3,
        "level": 5,
        "total_exp": 220
    },
    {
        "id": 7,
        "rarity": 4,
        "level": 0,
        "total_exp": 0
    },
    {
        "id": 8,
        "rarity": 4,
        "level": 1,
        "total_exp": 4
    },
    {
        "id": 9,
        "rarity": 4,
        "level": 2,
        "total_exp": 12
    },
    {
        "id": 10,
        "rarity": 4,
        "level": 3,
        "total_exp": 22
    },
    {
        "id": 11,
        "rarity": 4,
        "level": 4,
        "total_exp": 38
    },
    {
        "id": 12,
        "rarity": 4,
        "level": 5,
        "total_exp": 60
    },
    {
        "id": 13,
        "rarity": 5,
        "level": 0,
        "total_exp": 0
    },
    {
        "id": 14,
        "rarity": 5,
        "level": 1,
        "total_exp": 2
    },
    {
        "id": 15,
        "rarity": 5,
        "level": 2,
        "total_exp": 5
    },
    {
        "id": 16,
        "rarity": 5,
        "level": 3,
        "total_exp": 9
    },
    {
        "id": 17,
        "rarity": 5,
        "level": 4,
        "total_exp": 14
    },
    {
        "id": 18,
        "rarity": 5,
        "level": 5,
        "total_exp": 20
    }
]