[
    {
        "id": 101,
        "popup_id": 1,
        "page_number": 1,
        "ml_title": [
            "ターンとタイルの入れ替わり",
            ""
        ],
        "ml_description": [
            ""
        ]
    },
    {
        "id": 102,
        "popup_id": 1,
        "page_number": 2,
        "ml_title": [
            "移動と攻撃",
            ""
        ],
        "ml_description": [
            ""
        ]
    },
    {
        "id": 103,
        "popup_id": 1,
        "page_number": 3,
        "ml_title": [
            "すれ違いバフ",
            ""
        ],
        "ml_description": [
            ""
        ]
    },
    {
        "id": 104,
        "popup_id": 1,
        "page_number": 4,
        "ml_title": [
            "技法",
            ""
        ],
        "ml_description": [
            ""
        ]
    },
    {
        "id": 105,
        "popup_id": 1,
        "page_number": 5,
        "ml_title": [
            "入魂と絶技",
            ""
        ],
        "ml_description": [
            ""
        ]
    },
    {
        "id": 106,
        "popup_id": 1,
        "page_number": 6,
        "ml_title": [
            "右クリック",
            ""
        ],
        "ml_description": [
            ""
        ]
    },
    {
        "id": 107,
        "popup_id": 1,
        "page_number": 7,
        "ml_title": [
            "ターゲットオーダー",
            ""
        ],
        "ml_description": [
            ""
        ]
    },
    {
        "id": 201,
        "popup_id": 2,
        "page_number": 1,
        "ml_title": [
            "感情資源の回収",
            ""
        ],
        "ml_description": [
            "ミュージアム中央のバルーンをタップすると生産された感情資源を一括で回収できます。<br>感情資源は工房での創作や感情変換に使用します。",
            ""
        ]
    },
    {
        "id": 202,
        "popup_id": 2,
        "page_number": 2,
        "ml_title": [
            "ミュージアムの発展",
            ""
        ],
        "ml_description": [
            "工房などで美術品を獲得すると新たな展示ルームを開放出来る事があります。<br>新たに獲得した美術品は展示ルームに設置され、<br>美術品を集めるとミュージアムレベルが上がります。",
            ""
        ]
    },
    {
        "id": 203,
        "popup_id": 2,
        "page_number": 3,
        "ml_title": [
            "ミュージアムの機能",
            ""
        ],
        "ml_description": [
            "ミュージアムには感情資源の生産の他にも様々な機能があります。",
            ""
        ]
    },
    {
        "id": 204,
        "popup_id": 2,
        "page_number": 4,
        "ml_title": [
            "ミュージアムレベル",
            ""
        ],
        "ml_description": [
            "美術品レベルを上げていくとミュージアムレベルが上がり、感情資源の所持上限、<br>配置可能な学芸員数とAP回復量が上昇します。<br>また、感情変換の変換効率が良くなります。",
            ""
        ]
    },
    {
        "id": 205,
        "popup_id": 2,
        "page_number": 5,
        "ml_title": [
            "ミュージアムで起こること",
            ""
        ],
        "ml_description": [
            "ミュージアム内のオブジェクトはタップすると報酬がもらえる場合もあるので、<br>見つけたら積極的にタップしましょう。",
            ""
        ]
    },
    {
        "id": 301,
        "popup_id": 3,
        "page_number": 1,
        "ml_title": [
            "クエストについて",
            ""
        ],
        "ml_description": [
            "クエストでは藝術家を出撃させて戦うことになります。<br>また、イベントが開催されていればイベントにも出撃できます。<br>AP/BPはクエスト攻略に失敗した場合は消費されません。",
            ""
        ]
    },
    {
        "id": 401,
        "popup_id": 4,
        "page_number": 1,
        "ml_title": [
            "メインクエスト",
            ""
        ],
        "ml_description": [
            "メインクエストではステージに出撃することで手に入る「ストーリーキー」を用いて、<br>ストーリーを解放できます。",
            ""
        ]
    },
    {
        "id": 402,
        "popup_id": 4,
        "page_number": 2,
        "ml_title": [
            "ストーリーキーの入手",
            ""
        ],
        "ml_description": [
            "その章のバトルのステージをクリアした際のクリアランク=★の<br>合計数に応じてストーリーキーが入手できます。<br>STORYのステージのクリアランクは含みません。",
            ""
        ]
    },
    {
        "id": 403,
        "popup_id": 4,
        "page_number": 3,
        "ml_title": [
            "探索報酬",
            ""
        ],
        "ml_description": [
            "カウントと報酬は章ごとに独立していて、毎日リセットされます。<br>探求のクロノメーターを使用することですぐにリセットすることもできます。<br>クロノメーターによるリセット時には余剰カウントを使って探索報酬を獲得できます。",
            ""
        ]
    },
    {
        "id": 501,
        "popup_id": 5,
        "page_number": 1,
        "ml_title": [
            "出撃準備画面",
            ""
        ],
        "ml_description": [
            "バトルに出撃する前に、出撃チームの確認や調整、エネミーや報酬等の情報を<br>確認することができます。",
            ""
        ]
    },
    {
        "id": 502,
        "popup_id": 5,
        "page_number": 2,
        "ml_title": [
            "チーム",
            ""
        ],
        "ml_description": [
            "チーム情報から藝術家を選択すると、藝術家の技法やアクセサリ、イマージュ等を<br>変更することができます。",
            ""
        ]
    },
    {
        "id": 503,
        "popup_id": 5,
        "page_number": 3,
        "ml_title": [
            "クリアランクとスキップ",
            ""
        ],
        "ml_description": [
            "特定の条件を満たしてクリアすることで★にて表現されるクリアランクが達成され、<br>初回達成時に報酬がもらえます。★３評価を達成すると、<br>以降APやBP等のコストを消費して、バトルをスキップすることができます。",
            ""
        ]
    },
    {
        "id": 601,
        "popup_id": 6,
        "page_number": 1,
        "ml_title": [
            "リサーチクエスト",
            ""
        ],
        "ml_description": [
            "インスピレーション収集クエストと★の獲得総数による報酬は月ごとに切り替わります。<br>リサーチ挑戦券およびリサーチコインは翌月以降にも持ち越せます。",
            ""
        ]
    },
    {
        "id": 701,
        "popup_id": 7,
        "page_number": 1,
        "ml_title": [
            "ウィークリークエストとは",
            ""
        ],
        "ml_description": [
            "ウィークリークエストの探索報酬は曜日ごとに日替わりで、<br>探索報酬のクリアカウントは毎日リセットされます。",
            ""
        ]
    },
    {
        "id": 801,
        "popup_id": 8,
        "page_number": 1,
        "ml_title": [
            "創作とは",
            ""
        ],
        "ml_description": [
            "ミュージアムで獲得した感情資源を消費して創作を行い、<br>イマージュや美術品を獲得することができます。",
            ""
        ]
    },
    {
        "id": 802,
        "popup_id": 8,
        "page_number": 2,
        "ml_title": [
            "藝術家選択と資源設定",
            ""
        ],
        "ml_description": [
            "創作に使用する感情資源は、その消費量により完成する作品に影響が出ます。<br>創作履歴から藝術家選択と資源設定を参照することもできます。",
            ""
        ]
    },
    {
        "id": 803,
        "popup_id": 8,
        "page_number": 3,
        "ml_title": [
            "ポテンシャル発現について",
            ""
        ],
        "ml_description": [
            "工房でイマージュが創作される時、創作した藝術家に応じた<br>ポテンシャルが発現する場合があります。",
            ""
        ]
    },
    {
        "id": 804,
        "popup_id": 8,
        "page_number": 4,
        "ml_title": [
            "完成まで",
            ""
        ],
        "ml_description": [
            "創作を開始すると完成までの時間が表示されます。<br>完成時間が長いと貴重な作品の創作が期待できます。<br>即時完成には完成までの残り時間に応じた藝晶石を使用します。",
            ""
        ]
    },
    {
        "id": 805,
        "popup_id": 8,
        "page_number": 5,
        "ml_title": [
            "創作のヒント",
            ""
        ],
        "ml_description": [
            "創作に使用する4種の感情資源の配分によって、創作結果候補が決まります。<br>また、創作に使用した感情資源の合計量が多いと、<br>イマージュが創作される確率が高まります。",
            ""
        ]
    },
    {
        "id": 806,
        "popup_id": 8,
        "page_number": 6,
        "ml_title": [
            "創作道具",
            ""
        ],
        "ml_description": [
            "創作時に使用できる創作道具は各種類ごとに1つずつです。",
            ""
        ]
    },
    {
        "id": 901,
        "popup_id": 9,
        "page_number": 1,
        "ml_title": [
            "キャラクター",
            ""
        ],
        "ml_description": [
            "キャラクターでは藝術家とイマージュの各種強化や情報の確認などが行なえます。",
            ""
        ]
    },
    {
        "id": 1001,
        "popup_id": 10,
        "page_number": 1,
        "ml_title": [
            "パレット編集",
            ""
        ],
        "ml_description": [
            "パレットではスタイル・イマージュ・技法・アクセサリ<br>インスピレーション・行動タイプを設定できます。<br>設定された情報は編成で藝術家を配置する際に自動で読み込まれます。",
            ""
        ]
    },
    {
        "id": 1002,
        "popup_id": 10,
        "page_number": 2,
        "ml_title": [
            "スタイル",
            ""
        ],
        "ml_description": [
            "スタイルを変更するとカラー属性・通常攻撃・移動・絶技が変化します。<br>また、スタイルには得意なエレメントに補正がかかるエレメント補正を持ち、<br>対応する技法・絶技の威力が上昇します。",
            ""
        ]
    },
    {
        "id": 1003,
        "popup_id": 10,
        "page_number": 3,
        "ml_title": [
            "イマージュと絶技",
            ""
        ],
        "ml_description": [
            "イマージュを装備しないとすれ違いバフや入魂・絶技を使用することはできません。<br>絶技の射程や範囲、エレメントはイマージュが持ちます。",
            ""
        ]
    },
    {
        "id": 1004,
        "popup_id": 10,
        "page_number": 4,
        "ml_title": [
            "技法・アクセサリ・インスピレーション",
            ""
        ],
        "ml_description": [
            "アクセサリは一定レベルで特殊な効果を発揮します。<br>アクセサリ・インスピレーションは分解することで強化に使用する素材を獲得できます。",
            ""
        ]
    },
    {
        "id": 1005,
        "popup_id": 10,
        "page_number": 5,
        "ml_title": [
            "自動装着",
            ""
        ],
        "ml_description": [
            "自動装着は戦闘力が高くなるスタイル・イマージュ・技法・アクセサリが優先されます。",
            ""
        ]
    },
    {
        "id": 1101,
        "popup_id": 11,
        "page_number": 1,
        "ml_title": [
            "レベルアップ",
            ""
        ],
        "ml_description": [
            "藝術家の書を使用することで藝術家のレベルアップが行なえます。<br>レベルの上限は藝術家が持つスタイルの限界突破によって上昇します。",
            ""
        ]
    },
    {
        "id": 1102,
        "popup_id": 11,
        "page_number": 2,
        "ml_title": [
            "技法強化",
            ""
        ],
        "ml_description": [
            "強化素材はウィークリークエストやイベントなどで入手できます。",
            ""
        ]
    },
    {
        "id": 1103,
        "popup_id": 11,
        "page_number": 3,
        "ml_title": [
            "ベースアップ・命鏡変換",
            ""
        ],
        "ml_description": [
            "命鏡はイベント報酬や命鏡変換などで入手できます。命鏡変換ではオーブを<br>同レアリティの命鏡へ変換するほか、命鏡の高レアリティの命鏡への変換も可能です。<br>ベースアップは藝晶石を使用してリセットすることが可能です。",
            ""
        ]
    },
    {
        "id": 1104,
        "popup_id": 11,
        "page_number": 4,
        "ml_title": [
            "限界突破",
            ""
        ],
        "ml_description": [
            "藝術家のレベル上限・幸運と、スタイルに応じた熱情補正・絶技レベルが上昇します。<br>レアリティによって限界突破の回数に応じた追加ボーナス効果も獲得します。<br>オーブは同一スタイルの入手時に獲得できます。",
            ""
        ]
    },
    {
        "id": 1201,
        "popup_id": 12,
        "page_number": 1,
        "ml_title": [
            "交流とは",
            ""
        ],
        "ml_description": [
            "信愛レベルに応じて、藝術家のステータスに信愛ボーナスが加わります。<br>また、信愛レベル10では信愛ストーリーが解放されます。",
            ""
        ]
    },
    {
        "id": 1202,
        "popup_id": 12,
        "page_number": 2,
        "ml_title": [
            "エピソード",
            ""
        ],
        "ml_description": [
            "スタイルには固有のエピソードがあり、信愛度アイテムを使用することで解放できます。<br>エピソードは回想からも確認できます。",
            ""
        ]
    },
    {
        "id": 1301,
        "popup_id": 13,
        "page_number": 1,
        "ml_title": [
            "名簿とは",
            ""
        ],
        "ml_description": [
            "プロフィールは藝術家の信愛レベルに応じて解放されます。<br>スタイル情報ではSDキャラクターのタップにより立ち絵の確認も行えます。",
            ""
        ]
    },
    {
        "id": 1401,
        "popup_id": 14,
        "page_number": 1,
        "ml_title": [
            "イマージュ図録",
            ""
        ],
        "ml_description": [
            "図録では未入手のイマージュも含め、能力・プロフィールなどの情報を確認できます。",
            ""
        ]
    },
    {
        "id": 1501,
        "popup_id": 15,
        "page_number": 1,
        "ml_title": [
            "イマージュのレベルアップ",
            ""
        ],
        "ml_description": [
            "イマージュの書を使用しイマージュのレベルを上げると各パラメータ補正が上昇します。",
            ""
        ]
    },
    {
        "id": 1502,
        "popup_id": 15,
        "page_number": 2,
        "ml_title": [
            "一括合成とポテンシャル強化",
            ""
        ],
        "ml_description": [
            "一括合成では、経験値と素材としたイマージュの<br>ポテンシャルに応じたポテンシャルの強化が行えます。",
            ""
        ]
    },
    {
        "id": 1503,
        "popup_id": 15,
        "page_number": 3,
        "ml_title": [
            "ポテンシャルの継承",
            ""
        ],
        "ml_description": [
            "継承では、素材としたイマージュやポテンシャルジェムの<br>ポテンシャルに応じたポテンシャルの継承・強化が行えます。<br>ポテンシャルの枠数はレアリティによって決まります。",
            ""
        ]
    },
    {
        "id": 1504,
        "popup_id": 15,
        "page_number": 4,
        "ml_title": [
            "限界突破",
            ""
        ],
        "ml_description": [
            "イマージュの限界突破では絶技や入魂補正、すれ違いバフなどが強化されます。<br>限界突破の値は同一イマージュ間で共有され、<br>新しく同一イマージュを入手した際のレベルが上がります。",
            ""
        ]
    },
    {
        "id": 1601,
        "popup_id": 16,
        "page_number": 1,
        "ml_title": [
            "イマージュ一覧・別離",
            ""
        ],
        "ml_description": [
            "一覧ではイマージュとの別離が行なえます。別離をするとイマージュは失われます。",
            ""
        ]
    },
    {
        "id": 1701,
        "popup_id": 17,
        "page_number": 1,
        "ml_title": [
            "編成",
            ""
        ],
        "ml_description": [
            "藝術家最大５名で１つのチームを編成し、<br>作成済みのチームから１つを選んで出撃します。",
            ""
        ]
    },
    {
        "id": 1702,
        "popup_id": 17,
        "page_number": 2,
        "ml_title": [
            "デフォルトの装備",
            ""
        ],
        "ml_description": [
            "編成に藝術家をセットすると、イマージュ・技法などはパレットの情報が<br>自動的にセットされます。その後、チームに応じて内容の変更もできます。",
            ""
        ]
    },
    {
        "id": 1703,
        "popup_id": 17,
        "page_number": 3,
        "ml_title": [
            "パレットへの反映",
            ""
        ],
        "ml_description": [
            "デフォルトで参照されるパレットの設定は編成の内容で上書きすることも可能です。",
            ""
        ]
    },
    {
        "id": 1704,
        "popup_id": 17,
        "page_number": 4,
        "ml_title": [
            "おまかせ編成",
            ""
        ],
        "ml_description": [
            "おまかせ編成ボタンを選択すると、任意の属性に絞った編成を自動で行えます。",
            ""
        ]
    },
    {
        "id": 1801,
        "popup_id": 18,
        "page_number": 1,
        "ml_title": [
            "収集活動",
            ""
        ],
        "ml_description": [
            "期間限定で、対象アイテムの入手で収集点を獲得できます。<br>点数獲得の対象アイテムはバナーをチェックして確認しましょう。<br>獲得できる点数はアイテムによって異なります。",
            ""
        ]
    },
    {
        "id": 1802,
        "popup_id": 18,
        "page_number": 2,
        "ml_title": [
            "報酬とランキング",
            ""
        ],
        "ml_description": [
            "獲得した収集点が一定値に到達すると報酬を獲得できます。<br>収集活動終了時には開催期間中に獲得したポイント数によってランキング付けされ、<br>ランキングに応じた報酬も獲得できます。",
            ""
        ]
    },
    {
        "id": 1901,
        "popup_id": 19,
        "page_number": 1,
        "ml_title": [
            "回想",
            ""
        ],
        "ml_description": [
            "回想では、一度閲覧したストーリーの振り返りや、<br>キャラクター関連のストーリーの閲覧・解放ができます。",
            ""
        ]
    },
    {
        "id": 1902,
        "popup_id": 19,
        "page_number": 2,
        "ml_title": [
            "キャラクターのストーリー",
            ""
        ],
        "ml_description": [
            "藝術家やイマージュの物語の閲覧・解放ができます。<br>また、藝術家には信愛度アイテムをプレゼントし信愛度を上げることも可能です。",
            ""
        ]
    },
    {
        "id": 2001,
        "popup_id": 20,
        "page_number": 1,
        "ml_title": [
            "ランキング",
            ""
        ],
        "ml_description": [
            "「キャラクター」機能下の「藝術家：パレット」ページの情報を元に算出される<br>藝術家の戦闘力を合算した「総合戦闘力」に基づいたランキングです。",
            ""
        ]
    },
    {
        "id": 2002,
        "popup_id": 20,
        "page_number": 2,
        "ml_title": [
            "ランキングの種別",
            ""
        ],
        "ml_description": [
            "同程度の館長ランクのプレイヤー内でのランキングと、<br>全プレイヤー横断の無差別級の２種類があります。",
            ""
        ]
    },
    {
        "id": 2101,
        "popup_id": 21,
        "page_number": 1,
        "ml_title": [
            "執務室",
            ""
        ],
        "ml_description": [
            "プレイヤーの分身である館長のプロフィールやイベントでの実績の確認、<br>学芸員であるサンソヴィーノとの交流、調度品の設定などが行なえます。",
            ""
        ]
    },
    {
        "id": 2102,
        "popup_id": 21,
        "page_number": 2,
        "ml_title": [
            "学芸員情報",
            ""
        ],
        "ml_description": [
            "館長のランクが上昇するにつれ、サンソヴィーノの信愛レベルが上昇していきます。<br>一定に達すると、交流の物語が解放されていきます。",
            ""
        ]
    },
    {
        "id": 2103,
        "popup_id": 21,
        "page_number": 3,
        "ml_title": [
            "館長情報と調度品",
            ""
        ],
        "ml_description": [
            "館長名やコメントの編集、お気に入りの変更などができます。一部の情報は<br>他のプレイヤーがランキングなどからプロフィールを参照した際に表示されます。<br>調度品は勲章をショップで交換することで入手でき、最大３つまで配置できます。",
            ""
        ]
    },
    {
        "id": 2201,
        "popup_id": 22,
        "page_number": 1,
        "ml_title": [
            "ショップ",
            ""
        ],
        "ml_description": [
            "通貨の種類ごとにショップが分かれており、それぞれ対応した通貨が必要となります。<br>商品により購入制限が設定されている場合があります。<br>一部の商品は売り切れても一定期間で補充されます。",
            ""
        ]
    },
    {
        "id": 2202,
        "popup_id": 22,
        "page_number": 2,
        "ml_title": [
            "藝晶石",
            ""
        ],
        "ml_description": [
            "藝晶石はステージの初回報酬や一部のミッション等、特別な箇所で限られた数のみ<br>手に入る通貨です。ショップにて購入することも可能です。<br>購入した藝晶石についてはメニューの藝晶石所持状況から確認できます。",
            ""
        ]
    },
    {
        "id": 2203,
        "popup_id": 22,
        "page_number": 3,
        "ml_title": [
            "銀貨",
            ""
        ],
        "ml_description": [
            "クエストドロップや一部ミッションなど、ゲーム内の様々な場所で<br>獲得することができる通貨です。",
            ""
        ]
    },
    {
        "id": 2204,
        "popup_id": 22,
        "page_number": 4,
        "ml_title": [
            "交換所",
            ""
        ],
        "ml_description": [
            "交換所では通貨以外の特定アイテムを別のアイテムと交換することができます。<br>勲章はイベントランキングなどで、<br>ミラージュシルバーはイベント報酬などで入手できます。",
            ""
        ]
    },
    {
        "id": 2205,
        "popup_id": 22,
        "page_number": 5,
        "ml_title": [
            "月額パス",
            ""
        ],
        "ml_description": [
            "有効期間中に恩恵を得られるタイプのサブスクリプション商品です。<br>購入後、解約するまで自動的に更新されます。",
            ""
        ]
    },
    {
        "id": 2301,
        "popup_id": 23,
        "page_number": 1,
        "ml_title": [
            "ガチャ",
            ""
        ],
        "ml_description": [
            "ガチャを行うことで新たな藝術家のスタイルやイマージュを獲得することができます。<br>ガチャを行うには、ガチャごとに設定されている対価を必要とします。",
            ""
        ]
    },
    {
        "id": 2302,
        "popup_id": 23,
        "page_number": 2,
        "ml_title": [
            "重複したスタイル",
            ""
        ],
        "ml_description": [
            "オーブはスタイルの限界突破に使用します。<br>また、命鏡と交換することでベースアップにも使用できます。",
            ""
        ]
    },
    {
        "id": 2303,
        "popup_id": 23,
        "page_number": 3,
        "ml_title": [
            "マイレージ",
            ""
        ],
        "ml_description": [
            "マイレージが設定されているガチャは、<br>実行回数に応じてマイレージが溜まります。<br>マイレージはガチャ毎に独立して管理されます。",
            ""
        ]
    },
    {
        "id": 2401,
        "popup_id": 24,
        "page_number": 1,
        "ml_title": [
            "事前登録",
            ""
        ],
        "ml_description": [
            ""
        ]
    },
    {
        "id": 2402,
        "popup_id": 24,
        "page_number": 2,
        "ml_title": [
            "事前登録",
            ""
        ],
        "ml_description": [
            ""
        ]
    },
    {
        "id": 2501,
        "popup_id": 25,
        "page_number": 1,
        "ml_title": [
            "ボックスガチャ",
            ""
        ],
        "ml_description": [
            ""
        ]
    },
    {
        "id": 2601,
        "popup_id": 26,
        "page_number": 1,
        "ml_title": [
            "エピソード",
            ""
        ],
        "ml_description": [
            "イマージュには固有のエピソードがあり、入手したことのあるイマージュであれば<br>信愛度アイテムを使用することで解放できます。エピソードは回想からも確認できます。",
            ""
        ]
    },
    {
        "id": 2701,
        "popup_id": 27,
        "page_number": 1,
        "ml_title": [
            "キャンペーンガチャ",
            ""
        ],
        "ml_description": [
            ""
        ]
    },
    {
        "id": 2801,
        "popup_id": 28,
        "page_number": 1,
        "ml_title": [
            "メモリーとは",
            ""
        ],
        "ml_description": [
            "編成するとメモリー毎のメイン効果が発動し、バトルが有利に！<br>サブ効果は編成しなくても所持しているだけで藝術家全員に効果を発揮します。",
            ""
        ]
    },
    {
        "id": 2802,
        "popup_id": 28,
        "page_number": 2,
        "ml_title": [
            "メモリー機能説明",
            ""
        ],
        "ml_description": [
            "メモリーでは入手したメモリーの閲覧、強化、サブ効果の確認ができます。",
            ""
        ]
    },
    {
        "id": 2901,
        "popup_id": 29,
        "page_number": 1,
        "ml_title": [
            "ダンジョンとは",
            ""
        ],
        "ml_description": [
            "挑戦するたびに構造が変化するダンジョンを攻略し、最深フロアを目指します。<br>ダンジョンにはシーズンがあり、シーズン毎のルールは対象の全キャラクターに適用されます。",
            ""
        ]
    },
    {
        "id": 2902,
        "popup_id": 29,
        "page_number": 2,
        "ml_title": [
            "ダンジョンを探索しよう",
            ""
        ],
        "ml_description": [
            "感情資源を回収する際に得られる探索ポイント『シーカーズブーツ』を消費してダンジョン内を探索します。感情資源を回収出来ないとシーカーズブーツも獲得できないのでこまめに回収しましょう。",
            ""
        ]
    },
    {
        "id": 2903,
        "popup_id": 29,
        "page_number": 3,
        "ml_title": [
            "ダンジョンのマスの種類",
            ""
        ],
        "ml_description": [
            "ダンジョン探索中様々なイベントが発生します。イベントごとに必要な探索ポイントが決まっており、探索前にある程度予測が可能です。",
            ""
        ]
    },
    {
        "id": 2904,
        "popup_id": 29,
        "page_number": 4,
        "ml_title": [
            "フロアボスを倒して次のフロアへ",
            ""
        ],
        "ml_description": [
            "フロア内のボスを撃破する事で次のフロアへ進むことが出来るようになります。<br>同フロア内でより多くのイベントをクリアするとフロア移動時に踏破ボーナスが獲得できます。",
            ""
        ]
    },
    {
        "id": 2905,
        "popup_id": 29,
        "page_number": 5,
        "ml_title": [
            "ダンジョンショップで報酬交換",
            ""
        ],
        "ml_description": [
            "ダンジョンで獲得した専用ポイント『情動の枝』は専用ショップで報酬と交換できます。報酬はシーズンごとにリセットされるものもあるので、忘れず交換しましょう。所持中の情動の枝は次シーズンまで持ち越されます。",
            ""
        ]
    },
    {
        "id": 3001,
        "popup_id": 30,
        "page_number": 1,
        "ml_title": [
            "スペシャルクエスト",
            ""
        ],
        "ml_description": [
            "スペシャルクエストは期間限定で開催されます。<br>クリアランクの合計に応じて報酬が獲得できます。",
            ""
        ]
    },
    {
        "id": 3101,
        "popup_id": 31,
        "page_number": 1,
        "ml_title": [
            "アテネスレコード",
            ""
        ],
        "ml_description": [
            "アテネスレコードでは、地区ごとに分かれたマップのノードを解放することで<br>対応する藝術家に有効な効果を獲得できます。",
            ""
        ]
    },
    {
        "id": 3102,
        "popup_id": 31,
        "page_number": 2,
        "ml_title": [
            "スキルノードとロックノード",
            ""
        ],
        "ml_description": [
            "調査用ルーペと各地区に応じた水晶のペンデュラム・信愛度アップアイテムを使用して<br>スキルノードを解放できます。",
            ""
        ]
    },
    {
        "id": 3103,
        "popup_id": 31,
        "page_number": 3,
        "ml_title": [
            "マップレベル",
            ""
        ],
        "ml_description": [
            "イマージュの獲得・限界突破によりマップEXPを1獲得できます。",
            ""
        ]
    }
]